{"cc": "MY", "name": "Malaysia", "flag": "\ud83c\uddf2\ud83c\uddfe", "photos": 44658, "top_distinctive": [{"phrase": "singapore", "count": 15701, "score": 2.972}, {"phrase": "wildsingapore", "count": 13397, "score": 2.494}, {"phrase": "intertidal", "count": 12952, "score": 2.402}, {"phrase": "marinelife", "count": 12768, "score": 2.132}, {"phrase": "seashore", "count": 12983, "score": 2.086}, {"phrase": "shore", "count": 12858, "score": 1.993}, {"phrase": "marine", "count": 13229, "score": 1.728}, {"phrase": "coastal", "count": 8652, "score": 1.451}, {"phrase": "wildlife", "count": 14483, "score": 1.386}, {"phrase": "underwater", "count": 12552, "score": 1.304}, {"phrase": "pulau", "count": 7289, "score": 1.27}, {"phrase": "ubin", "count": 5233, "score": 0.946}, {"phrase": "island", "count": 13188, "score": 0.787}, {"phrase": "nature", "count": 14600, "score": 0.704}, {"phrase": "kuala lumpur", "count": 3974, "score": 0.696}], "top_raw": [{"phrase": "singapore", "count": 15701}, {"phrase": "nature", "count": 14600}, {"phrase": "wildlife", "count": 14483}, {"phrase": "wildsingapore", "count": 13397}, {"phrase": "marine", "count": 13229}, {"phrase": "island", "count": 13188}, {"phrase": "seashore", "count": 12983}, {"phrase": "intertidal", "count": 12952}, {"phrase": "shore", "count": 12858}, {"phrase": "marinelife", "count": 12768}, {"phrase": "underwater", "count": 12552}, {"phrase": "coastal", "count": 8652}, {"phrase": "pulau", "count": 7289}, {"phrase": "ubin", "count": 5233}, {"phrase": "kuala lumpur", "count": 3974}, {"phrase": "changi", "count": 3622}, {"phrase": "asia", "count": 3020}, {"phrase": "beach", "count": 2229}, {"phrase": "cnidaria", "count": 2135}, {"phrase": "kuala", "count": 2028}, {"phrase": "chek jawa", "count": 1975}, {"phrase": "sabah", "count": 1946}, {"phrase": "mangroves", "count": 1883}, {"phrase": "food", "count": 1872}, {"phrase": "mollusca", "count": 1732}], "admins": [{"admin1": "Johor", "total": 193601, "top_phrases": [{"phrase": "singapore", "count": 15618}, {"phrase": "nature", "count": 13567}, {"phrase": "wildsingapore", "count": 13397}, {"phrase": "wildlife", "count": 13386}, {"phrase": "marine", "count": 13158}, {"phrase": "seashore", "count": 12979}]}, {"admin1": "Perak", "total": 23835, "top_phrases": [{"phrase": "pangkor", "count": 754}, {"phrase": "food", "count": 735}, {"phrase": "island", "count": 725}, {"phrase": "beach", "count": 717}, {"phrase": "sea", "count": 702}, {"phrase": "flora", "count": 698}]}, {"admin1": "Kuala Lumpur", "total": 18968, "top_phrases": [{"phrase": "lumpur", "count": 929}, {"phrase": "kuala", "count": 923}, {"phrase": "asia", "count": 777}, {"phrase": "basketball", "count": 615}, {"phrase": "food", "count": 535}, {"phrase": "bball", "count": 513}]}, {"admin1": "Sabah", "total": 13578, "top_phrases": [{"phrase": "borneo", "count": 1126}, {"phrase": "kota kinabalu", "count": 728}, {"phrase": "thienzieyung", "count": 713}, {"phrase": "kinabalu", "count": 470}, {"phrase": "places", "count": 399}, {"phrase": "trees", "count": 346}]}, {"admin1": "Negeri Sembilan", "total": 11481, "top_phrases": [{"phrase": "port dickson", "count": 665}, {"phrase": "hotel", "count": 588}, {"phrase": "resort", "count": 572}, {"phrase": "beach", "count": 400}, {"phrase": "nature", "count": 380}, {"phrase": "water", "count": 373}]}, {"admin1": "Selangor", "total": 7111, "top_phrases": [{"phrase": "kuala", "count": 520}, {"phrase": "lumpur", "count": 419}, {"phrase": "event", "count": 410}, {"phrase": "asia", "count": 262}, {"phrase": "hardy", "count": 218}, {"phrase": "sham", "count": 218}]}, {"admin1": "Penang", "total": 6934, "top_phrases": [{"phrase": "georgetown", "count": 359}, {"phrase": "pinang", "count": 274}, {"phrase": "beach", "count": 218}, {"phrase": "hotel", "count": 204}, {"phrase": "pulau", "count": 191}, {"phrase": "batu", "count": 179}]}, {"admin1": "Pahang", "total": 5492, "top_phrases": [{"phrase": "tioman", "count": 360}, {"phrase": "diving", "count": 302}, {"phrase": "cameron highlands", "count": 240}, {"phrase": "kuantan", "count": 148}, {"phrase": "hotel", "count": 112}, {"phrase": "swimming", "count": 107}]}, {"admin1": "Sarawak", "total": 3129, "top_phrases": [{"phrase": "borneo", "count": 437}, {"phrase": "kuching", "count": 352}, {"phrase": "national park", "count": 94}, {"phrase": "river", "count": 75}, {"phrase": "rejang", "count": 69}, {"phrase": "bako national park", "count": 56}]}, {"admin1": "Terengganu", "total": 3074, "top_phrases": [{"phrase": "beach", "count": 176}, {"phrase": "perhentian", "count": 129}, {"phrase": "redang", "count": 128}, {"phrase": "island", "count": 122}, {"phrase": "kuala terengganu", "count": 92}, {"phrase": "ocean", "count": 73}]}, {"admin1": "Kedah", "total": 2661, "top_phrases": [{"phrase": "langkawi", "count": 364}, {"phrase": "jusni", "count": 257}, {"phrase": "jusni nasirun", "count": 257}, {"phrase": "film", "count": 198}, {"phrase": "om-2n", "count": 88}, {"phrase": "thailand", "count": 81}]}, {"admin1": "Putrajaya", "total": 2642, "top_phrases": [{"phrase": "balloon", "count": 150}, {"phrase": "air", "count": 145}, {"phrase": "hot", "count": 145}, {"phrase": "kuala", "count": 133}, {"phrase": "lumpur", "count": 133}, {"phrase": "festival", "count": 129}]}, {"admin1": "Melaka", "total": 2301, "top_phrases": [{"phrase": "malacca", "count": 403}, {"phrase": "asia", "count": 92}, {"phrase": "architecture", "count": 40}, {"phrase": "inn", "count": 38}, {"phrase": "temple", "count": 33}, {"phrase": "dutch", "count": 32}]}, {"admin1": "Kelantan", "total": 1705, "top_phrases": [{"phrase": "bus", "count": 119}, {"phrase": "kota bharu", "count": 90}, {"phrase": "train", "count": 64}, {"phrase": "route", "count": 49}, {"phrase": "blog5106", "count": 48}, {"phrase": "city bus", "count": 48}]}, {"admin1": "Perlis", "total": 1128, "top_phrases": [{"phrase": "jusni", "count": 265}, {"phrase": "jusni nasirun", "count": 265}, {"phrase": "film", "count": 226}, {"phrase": "om-2n", "count": 46}, {"phrase": "electro", "count": 27}, {"phrase": "yashica", "count": 27}]}], "cities": [{"admin1": "Johor", "city": "Kampung Pasir Gudang Baru", "total": 157556, "top_phrases": [{"phrase": "singapore", "count": 12394}, {"phrase": "nature", "count": 11310}, {"phrase": "wildsingapore", "count": 11295}, {"phrase": "wildlife", "count": 11257}, {"phrase": "marine", "count": 11164}, {"phrase": "seashore", "count": 11060}]}, {"admin1": "Johor", "city": "Johor Bahru", "total": 27978, "top_phrases": [{"phrase": "singapore", "count": 3207}, {"phrase": "nature", "count": 2241}, {"phrase": "wildlife", "count": 2098}, {"phrase": "wildsingapore", "count": 2067}, {"phrase": "marine", "count": 1987}, {"phrase": "seashore", "count": 1908}]}, {"admin1": "Perak", "city": "Lumut", "total": 15849, "top_phrases": [{"phrase": "pangkor", "count": 754}, {"phrase": "island", "count": 724}, {"phrase": "beach", "count": 715}, {"phrase": "sea", "count": 699}, {"phrase": "fauna", "count": 693}, {"phrase": "food", "count": 680}]}, {"admin1": "Kuala Lumpur", "city": "Kuala Lumpur", "total": 15645, "top_phrases": [{"phrase": "lumpur", "count": 903}, {"phrase": "kuala", "count": 900}, {"phrase": "asia", "count": 771}, {"phrase": "basketball", "count": 605}, {"phrase": "food", "count": 523}, {"phrase": "bball", "count": 502}]}, {"admin1": "Negeri Sembilan", "city": "Port Dickson", "total": 8412, "top_phrases": [{"phrase": "hotel", "count": 585}, {"phrase": "resort", "count": 571}, {"phrase": "beach", "count": 399}, {"phrase": "nature", "count": 377}, {"phrase": "chalet", "count": 369}, {"phrase": "water", "count": 369}]}, {"admin1": "Sabah", "city": "Kota Kinabalu", "total": 6406, "top_phrases": [{"phrase": "thienzieyung", "count": 511}, {"phrase": "places", "count": 292}, {"phrase": "geography", "count": 246}, {"phrase": "borneo", "count": 245}, {"phrase": "cars", "count": 241}, {"phrase": "trees", "count": 228}]}, {"admin1": "Johor", "city": "Skudai", "total": 5075, "top_phrases": [{"phrase": "utm", "count": 473}, {"phrase": "beauty beast", "count": 407}, {"phrase": "tesl", "count": 326}, {"phrase": "theatre", "count": 326}, {"phrase": "student", "count": 284}, {"phrase": "dsi", "count": 264}]}, {"admin1": "Selangor", "city": "Petaling Jaya", "total": 4565, "top_phrases": [{"phrase": "kuala", "count": 385}, {"phrase": "lumpur", "count": 385}, {"phrase": "event", "count": 319}, {"phrase": "asia", "count": 236}, {"phrase": "damansara", "count": 218}, {"phrase": "music", "count": 178}]}, {"admin1": "Johor", "city": "Mersing", "total": 4390, "top_phrases": [{"phrase": "beach", "count": 353}, {"phrase": "golf", "count": 347}, {"phrase": "kuala", "count": 347}, {"phrase": "lanjut", "count": 347}, {"phrase": "rompin", "count": 347}, {"phrase": "htan", "count": 310}]}, {"admin1": "Penang", "city": "Tanjung Tokong", "total": 3605, "top_phrases": [{"phrase": "beach", "count": 201}, {"phrase": "hotel", "count": 190}, {"phrase": "pinang", "count": 180}, {"phrase": "batu", "count": 179}, {"phrase": "ferringhi", "count": 175}, {"phrase": "pulau", "count": 175}]}, {"admin1": "Sabah", "city": "Ranau", "total": 3147, "top_phrases": [{"phrase": "borneo", "count": 350}, {"phrase": "kinabalu", "count": 268}, {"phrase": "kundasang", "count": 147}, {"phrase": "park", "count": 142}, {"phrase": "national", "count": 141}, {"phrase": "animals", "count": 140}]}, {"admin1": "Putrajaya", "city": "Putrajaya", "total": 2488, "top_phrases": [{"phrase": "balloon", "count": 150}, {"phrase": "air", "count": 145}, {"phrase": "hot", "count": 145}, {"phrase": "kuala", "count": 133}, {"phrase": "lumpur", "count": 133}, {"phrase": "festival", "count": 129}]}, {"admin1": "Penang", "city": "George Town", "total": 2467, "top_phrases": [{"phrase": "georgetown", "count": 297}, {"phrase": "asia", "count": 98}, {"phrase": "temple", "count": 94}, {"phrase": "pinang", "count": 93}, {"phrase": "kek lok", "count": 56}, {"phrase": "chinese", "count": 55}]}, {"admin1": "Pahang", "city": "Kuantan", "total": 2355, "top_phrases": [{"phrase": "mall", "count": 103}, {"phrase": "hotel", "count": 101}, {"phrase": "makmur", "count": 101}, {"phrase": "annual", "count": 100}, {"phrase": "association", "count": 100}, {"phrase": "coast", "count": 100}]}, {"admin1": "Sarawak", "city": "Kuching", "total": 1888, "top_phrases": [{"phrase": "borneo", "count": 264}, {"phrase": "national park", "count": 71}, {"phrase": "bako national park", "count": 56}, {"phrase": "bako", "count": 52}, {"phrase": "wildlife", "count": 48}, {"phrase": "monkey", "count": 46}]}, {"admin1": "Melaka", "city": "Malacca", "total": 1875, "top_phrases": [{"phrase": "asia", "count": 76}, {"phrase": "architecture", "count": 39}, {"phrase": "inn", "count": 38}, {"phrase": "dutch", "count": 31}, {"phrase": "temple", "count": 31}, {"phrase": "church", "count": 31}]}, {"admin1": "Pahang", "city": "Kampung Tekek", "total": 1717, "top_phrases": [{"phrase": "tioman", "count": 360}, {"phrase": "diving", "count": 302}, {"phrase": "salang", "count": 106}, {"phrase": "island", "count": 76}, {"phrase": "tioman island", "count": 53}, {"phrase": "scuba", "count": 51}]}, {"admin1": "Pahang", "city": "Tanah Rata", "total": 1390, "top_phrases": [{"phrase": "cameron highlands", "count": 240}, {"phrase": "cameron", "count": 94}, {"phrase": "highlands", "count": 91}, {"phrase": "asia", "count": 73}, {"phrase": "highland", "count": 49}, {"phrase": "farm", "count": 43}]}, {"admin1": "Kedah", "city": "Kuah", "total": 1360, "top_phrases": [{"phrase": "langkawi", "count": 364}, {"phrase": "thailand", "count": 80}, {"phrase": "sea", "count": 63}, {"phrase": "beach", "count": 49}, {"phrase": "koh adang", "count": 47}, {"phrase": "island", "count": 39}]}, {"admin1": "Negeri Sembilan", "city": "Kampung Baharu Nilai", "total": 1306, "top_phrases": [{"phrase": "sepang", "count": 151}, {"phrase": "racing", "count": 113}, {"phrase": "formula1", "count": 90}, {"phrase": "malaysiangp2007", "count": 87}, {"phrase": "f1sepang07", "count": 86}, {"phrase": "grandprix", "count": 46}]}, {"admin1": "Terengganu", "city": "Kuala Terengganu", "total": 1276, "top_phrases": [{"phrase": "redang", "count": 125}, {"phrase": "beach", "count": 74}, {"phrase": "island", "count": 62}, {"phrase": "pulau redang", "count": 56}, {"phrase": "analog", "count": 47}, {"phrase": "film", "count": 47}]}, {"admin1": "Perak", "city": "Ipoh", "total": 1162, "top_phrases": [{"phrase": "history", "count": 86}, {"phrase": "food", "count": 41}, {"phrase": "genealogy", "count": 35}, {"phrase": "shchow", "count": 32}, {"phrase": "sheu hau chow", "count": 32}, {"phrase": "asia", "count": 30}]}, {"admin1": "Selangor", "city": "Kampong Baharu Balakong", "total": 1152, "top_phrases": [{"phrase": "bukit jalil", "count": 93}, {"phrase": "hardy", "count": 92}, {"phrase": "sham", "count": 92}, {"phrase": "energizer strike", "count": 91}, {"phrase": "event", "count": 91}, {"phrase": "paintball", "count": 91}]}, {"admin1": "Sabah", "city": "Sandakan", "total": 1097, "top_phrases": [{"phrase": "borneo", "count": 181}, {"phrase": "kinabatangan river", "count": 54}, {"phrase": "rainforest", "count": 44}, {"phrase": "east malaysia", "count": 39}, {"phrase": "hornbill", "count": 35}, {"phrase": "deforestation", "count": 31}]}, {"admin1": "Sabah", "city": "Semporna", "total": 1075, "top_phrases": [{"phrase": "sipadan", "count": 124}, {"phrase": "borneo", "count": 92}, {"phrase": "diving", "count": 72}, {"phrase": "underwater", "count": 65}, {"phrase": "scuba", "count": 60}, {"phrase": "mabul", "count": 56}]}, {"admin1": "Terengganu", "city": "Cukai", "total": 1073, "top_phrases": [{"phrase": "cherating", "count": 68}, {"phrase": "kuantan", "count": 64}, {"phrase": "beach", "count": 58}, {"phrase": "pahang", "count": 58}, {"phrase": "kemaman", "count": 56}, {"phrase": "resort", "count": 54}]}, {"admin1": "Sabah", "city": "Donggongon", "total": 1040, "top_phrases": [{"phrase": "thienzieyung", "count": 97}, {"phrase": "kota kinabalu", "count": 87}, {"phrase": "cars", "count": 46}, {"phrase": "trees", "count": 44}, {"phrase": "vehicles", "count": 43}, {"phrase": "borneo", "count": 40}]}, {"admin1": "Pahang", "city": "Kampung Bukit Tinggi, Bentong", "total": 1039, "top_phrases": [{"phrase": "genting highlands", "count": 73}, {"phrase": "highland", "count": 50}, {"phrase": "colmar tropicale", "count": 47}, {"phrase": "theme park", "count": 44}, {"phrase": "ccip", "count": 43}, {"phrase": "mmu", "count": 43}]}, {"admin1": "Kedah", "city": "Jitra", "total": 935, "top_phrases": [{"phrase": "jusni", "count": 178}, {"phrase": "jusni nasirun", "count": 178}, {"phrase": "film", "count": 127}, {"phrase": "om-2n", "count": 64}, {"phrase": "scanned negative", "count": 60}, {"phrase": "superia", "count": 24}]}, {"admin1": "Penang", "city": "Bukit Mertajam", "total": 850, "top_phrases": [{"phrase": "toy", "count": 53}, {"phrase": "art", "count": 45}, {"phrase": "be%40rbrick", "count": 45}, {"phrase": "bearbrick", "count": 45}, {"phrase": "collectible", "count": 45}, {"phrase": "designer", "count": 45}]}], "samples": [{"photoid": 3900216592, "key": "0406258e1457f2e5ec91163d4d2d", "shard": "040", "lat": 1.376581, "lon": 104.004735, "admin1": "Johor", "city": "Kampung Pasir Gudang Baru", "title": "Polka-dotted+sea+cucumber+%28Bohadschia+ocellata%29", "usertags": "changi,echinodermata,holothuria,holothuroidea,intertidal,marine,marinelife,nature,ocellata,seashore,shore,singapore,sland,underwater,wildlife,wildsingapore", "downloadurl": "http://farm3.staticflickr.com/2571/3900216592_de8d887bb1.jpg", "top_phrases": ["changi", "echinodermata", "holothuria", "holothuroidea", "intertidal", "marine", "marinelife", "nature", "ocellata", "seashore"]}, {"photoid": 9322765607, "key": "0c097aea1bf25a24fda146889bdacd2", "shard": "0c0", "lat": 1.376581, "lon": 104.004735, "admin1": "Johor", "city": "Kampung Pasir Gudang Baru", "title": "Unidentified+colonial+ascidians", "usertags": "ascidiacea,carpark+7,changi,coastal,intertidal,island,marine,marinelife,nature,seashore,shore,singapore,underwater,wildlife,wildsingapore", "downloadurl": "http://farm8.staticflickr.com/7296/9322765607_f7cde737f6.jpg", "top_phrases": ["ascidiacea", "carpark", "changi", "coastal", "intertidal", "island", "marine", "marinelife", "nature", "seashore"]}, {"photoid": 3138154510, "key": "1809f4db6abd084238b8bf9e4b96b1a", "shard": "180", "lat": 1.387231, "lon": 103.942508, "admin1": "Johor", "city": "Kampung Pasir Gudang Baru", "title": "Tiny+flower+crabs+%28Portunus+pelagicus%29", "usertags": "crustacea,intertidal,island,marine,marinelife,nature,pasir+ris,pelagicus,portunus,seashore,shore,singapore,underwater,wildlife,wildsingapore", "downloadurl": "http://farm4.staticflickr.com/3083/3138154510_5a748cf088.jpg", "top_phrases": ["crustacea", "intertidal", "island", "marine", "marinelife", "nature", "pasir ris", "pelagicus", "portunus", "seashore"]}, {"photoid": 3579544721, "key": "1804e8b83448a2cd61fa87aab4e8166", "shard": "180", "lat": 6.382177, "lon": 100.162353, "admin1": "Perlis", "city": "Kuala Perlis", "title": "My+Oly+family", "usertags": "camera,explore,jusni,jusni+nasirun,olympus+om1,om2n,om2sp+olympus+om1+om2n,porn", "downloadurl": "http://farm3.staticflickr.com/2471/3579544721_cc6e158fd0.jpg", "top_phrases": ["explore", "jusni", "jusni nasirun", "om1", "om2n", "om2sp om1 om2n", "porn"]}, {"photoid": 7384677818, "key": "1c0b6856a519cb72c7f21e2b79dcea7", "shard": "1c0", "lat": 1.376581, "lon": 104.004735, "admin1": "Johor", "city": "Kampung Pasir Gudang Baru", "title": "Living+shores+of+Changi", "usertags": "changi,coastal,intertidal,island,landscape,marine,marinelife,nature,seagrasses,seashore,shore,singapore,underwater,wildlife,wildsingapore", "downloadurl": "http://farm8.staticflickr.com/7083/7384677818_4f557c00f0.jpg", "top_phrases": ["changi", "coastal", "intertidal", "island", "marine", "marinelife", "nature", "seagrasses", "seashore", "shore"]}, {"photoid": 8340394727, "key": "1c092d1f13eb682f6e19dbeaacd4", "shard": "1c0", "lat": 3.148833, "lon": 101.713166, "admin1": "Kuala Lumpur", "city": "Kuala Lumpur", "title": "Now+I%27m+at+Dragon-I+...+A+little+bit+of+hospitality+first", "usertags": "", "downloadurl": "http://farm9.staticflickr.com/8360/8340394727_2bec4617a5.jpg", "top_phrases": []}, {"photoid": 12084583493, "key": "1c0557cde763f152ff6c14b9f74a", "shard": "1c0", "lat": 1.408318, "lon": 103.990831, "admin1": "Johor", "city": "Kampung Pasir Gudang Baru", "title": "Keyhole+sand+dollar+%28Echinodiscus+sp.%29", "usertags": "bisperforatus,chek,coastal,echinodermata,echinodiscus,echinoidea,intertidal,island,jawa,marine,marinelife,nature,pulau,seashore,shore,singapore,truncatus,ubin,underwater,wildlife,wildsingapore", "downloadurl": "http://farm4.staticflickr.com/3782/12084583493_ea143af15d.jpg", "top_phrases": ["bisperforatus", "chek", "coastal", "echinodermata", "echinodiscus", "echinoidea", "intertidal", "island", "jawa", "marine"]}, {"photoid": 6991624317, "key": "2001f695cc9cf96548de0776263767", "shard": "200", "lat": 1.410313, "lon": 103.994007, "admin1": "Johor", "city": "Kampung Pasir Gudang Baru", "title": "Cake+sand+dollar+%28Arachnoides+placenta%29+overturned+and+pecked+by+shorebirds", "usertags": "arachnoides,chek+jawa,echinodermata,echinoidea,intertidal,island,marine,marinelife,nature,placenta,pulau,seashore,shore,singapore,ubin,underwater,wildlife,wildsingapore", "downloadurl": "http://farm8.staticflickr.com/7048/6991624317_bb1903f5ed.jpg", "top_phrases": ["arachnoides", "chek jawa", "echinodermata", "echinoidea", "intertidal", "island", "marine", "marinelife", "nature", "placenta"]}, {"photoid": 8287831243, "key": "200f0bed273b240caaa73d0f23bb6da", "shard": "200", "lat": 2.732921, "lon": 102.001937, "admin1": "Negeri Sembilan", "city": "Seremban", "title": "I+think+I%27m+a+gorilla.+Mmm+or+a+monkey%3F+Wait%2C+I+can%27t+sit+down+properly.+Hehe+Yea%2C+I%27m+a+gorilla.+Thanks+%40thejoezakaria+%21", "usertags": "", "downloadurl": "http://farm9.staticflickr.com/8348/8287831243_cc86dbbdec.jpg", "top_phrases": []}, {"photoid": 8282130135, "key": "2408c047e41d62d75749876234b5b1", "shard": "240", "lat": 1.553859, "lon": 110.341873, "admin1": "Sarawak", "city": "Kuching", "title": "20121123_0947+Kuching+Civic+Centre+mid+day+panorama", "usertags": "kuching,sarawak", "downloadurl": "http://farm9.staticflickr.com/8348/8282130135_f27964c438.jpg", "top_phrases": ["kuching", "sarawak"]}, {"photoid": 345288080, "key": "280c541d60ed9316ebf255569deff5", "shard": "280", "lat": 1.553345, "lon": 103.635749, "admin1": "Johor", "city": "Skudai", "title": "Eid+Adha%3AFizah+Open+House", "usertags": "blogging,eid+adah,friends,johor,malay,malaysian,people,photography,random,utm", "downloadurl": "http://farm1.staticflickr.com/152/345288080_35464c1eb9.jpg", "top_phrases": ["blogging", "eid adah", "friends", "johor", "malay", "malaysian", "people", "photography", "random", "utm"]}, {"photoid": 366503749, "key": "280a076a5f75262ee71476ad8bfd5f", "shard": "280", "lat": 3.132288, "lon": 101.704902, "admin1": "Kuala Lumpur", "city": "Kuala Lumpur", "title": "Tamil+dance", "usertags": "kuala+lumpur,turkka%27s+and+anita%27s+wedding", "downloadurl": "http://farm1.staticflickr.com/135/366503749_51df4f43b7.jpg", "top_phrases": ["kuala lumpur", "turkka%27s anita%27s wedding"]}, {"photoid": 4297572738, "key": "280cd57eaa8e348a6fda4c3fcf28f", "shard": "280", "lat": 6.513179, "lon": 99.312286, "admin1": "Kedah", "city": "Kuah", "title": "Christmas+Dress", "usertags": "christmas,dress,red", "downloadurl": "http://farm3.staticflickr.com/2801/4297572738_64e8f8ed92.jpg", "top_phrases": ["christmas", "dress", "red"]}, {"photoid": 4404726183, "key": "280a14e4149160e70b8ed3f72b347", "shard": "280", "lat": 5.920902, "lon": 102.722243, "admin1": "Terengganu", "city": "Jertih", "title": "Breakfast+view+at+Bubu+Resort", "usertags": "mobile", "downloadurl": "http://farm3.staticflickr.com/2684/4404726183_ab0428318a.jpg", "top_phrases": ["mobile"]}]}