{"cc": "BB", "name": "BB", "flag": "", "photos": 1239, "top_distinctive": [{"phrase": "barbados", "count": 1259, "score": 8.308}, {"phrase": "caribbean", "count": 454, "score": 1.214}, {"phrase": "bridgetown", "count": 118, "score": 0.521}, {"phrase": "scenery", "count": 152, "score": 0.503}, {"phrase": "ocean", "count": 268, "score": 0.447}, {"phrase": "indies", "count": 108, "score": 0.333}, {"phrase": "tropical", "count": 142, "score": 0.302}, {"phrase": "west", "count": 108, "score": 0.299}, {"phrase": "island", "count": 203, "score": 0.297}, {"phrase": "beach", "count": 228, "score": 0.28}, {"phrase": "atlantic", "count": 88, "score": 0.26}, {"phrase": "cruise", "count": 127, "score": 0.245}, {"phrase": "sea", "count": 174, "score": 0.21}, {"phrase": "prospect bay", "count": 45, "score": 0.159}, {"phrase": "waves hotel", "count": 45, "score": 0.159}], "top_raw": [{"phrase": "barbados", "count": 1259}, {"phrase": "caribbean", "count": 454}, {"phrase": "ocean", "count": 268}, {"phrase": "beach", "count": 228}, {"phrase": "island", "count": 203}, {"phrase": "sea", "count": 174}, {"phrase": "scenery", "count": 152}, {"phrase": "tropical", "count": 142}, {"phrase": "water", "count": 133}, {"phrase": "cruise", "count": 127}, {"phrase": "bridgetown", "count": 118}, {"phrase": "indies", "count": 108}, {"phrase": "west", "count": 108}, {"phrase": "atlantic", "count": 88}, {"phrase": "sunset", "count": 82}, {"phrase": "sand", "count": 55}, {"phrase": "flowers", "count": 54}, {"phrase": "seadream", "count": 50}, {"phrase": "waves", "count": 50}, {"phrase": "sun", "count": 47}, {"phrase": "ship", "count": 47}, {"phrase": "prospect bay", "count": 45}, {"phrase": "james", "count": 45}, {"phrase": "waves hotel", "count": 45}, {"phrase": "plants", "count": 44}], "admins": [{"admin1": "Saint Michael", "total": 1528, "top_phrases": [{"phrase": "barbados", "count": 344}, {"phrase": "caribbean", "count": 155}, {"phrase": "bridgetown", "count": 117}, {"phrase": "cruise", "count": 116}, {"phrase": "beach", "count": 73}, {"phrase": "ocean", "count": 65}]}, {"admin1": "Saint James", "total": 1264, "top_phrases": [{"phrase": "barbados", "count": 277}, {"phrase": "caribbean", "count": 82}, {"phrase": "island", "count": 79}, {"phrase": "tropical", "count": 50}, {"phrase": "scenery", "count": 48}, {"phrase": "ocean", "count": 46}]}, {"admin1": "Saint Joseph", "total": 1186, "top_phrases": [{"phrase": "barbados", "count": 191}, {"phrase": "caribbean", "count": 73}, {"phrase": "scenery", "count": 68}, {"phrase": "ocean", "count": 63}, {"phrase": "island", "count": 58}, {"phrase": "tropical", "count": 53}]}, {"admin1": "Christ Church", "total": 703, "top_phrases": [{"phrase": "barbados", "count": 209}, {"phrase": "caribbean", "count": 69}, {"phrase": "beach", "count": 57}, {"phrase": "ocean", "count": 52}, {"phrase": "sea", "count": 38}, {"phrase": "oistins", "count": 21}]}, {"admin1": "Saint Andrew", "total": 425, "top_phrases": [{"phrase": "barbados", "count": 63}, {"phrase": "island", "count": 22}, {"phrase": "water", "count": 19}, {"phrase": "atlantic", "count": 18}, {"phrase": "coast", "count": 18}, {"phrase": "coastline", "count": 18}]}, {"admin1": "Saint Philip", "total": 342, "top_phrases": [{"phrase": "barbados", "count": 52}, {"phrase": "caribbean", "count": 30}, {"phrase": "kristina cruises", "count": 18}, {"phrase": "outdoors", "count": 15}, {"phrase": "sea", "count": 13}, {"phrase": "background", "count": 12}]}, {"admin1": "Saint Lucy", "total": 205, "top_phrases": [{"phrase": "barbados", "count": 28}, {"phrase": "caribbean", "count": 12}, {"phrase": "sea", "count": 7}, {"phrase": "island", "count": 6}, {"phrase": "autopanopro", "count": 5}, {"phrase": "backside", "count": 5}]}, {"admin1": "Saint John", "total": 155, "top_phrases": [{"phrase": "barbados", "count": 36}, {"phrase": "caribbean", "count": 10}, {"phrase": "islands", "count": 8}, {"phrase": "ocean", "count": 6}, {"phrase": "island", "count": 6}, {"phrase": "beach", "count": 5}]}, {"admin1": "Saint Thomas", "total": 146, "top_phrases": [{"phrase": "barbados", "count": 39}, {"phrase": "cave", "count": 15}, {"phrase": "harrison%27s cave", "count": 14}, {"phrase": "caribbean", "count": 14}, {"phrase": "gun hill signal station", "count": 11}, {"phrase": "green", "count": 4}]}, {"admin1": "Saint Peter", "total": 99, "top_phrases": [{"phrase": "barbados", "count": 20}, {"phrase": "sea", "count": 8}, {"phrase": "ocean", "count": 7}, {"phrase": "beach", "count": 7}, {"phrase": "sunset", "count": 5}, {"phrase": "sand", "count": 4}]}], "cities": [{"admin1": "Saint Michael", "city": "Bridgetown", "total": 1343, "top_phrases": [{"phrase": "barbados", "count": 344}, {"phrase": "caribbean", "count": 155}, {"phrase": "cruise", "count": 116}, {"phrase": "beach", "count": 73}, {"phrase": "ocean", "count": 65}, {"phrase": "seadream", "count": 50}]}, {"admin1": "Saint James", "city": "Holetown", "total": 1083, "top_phrases": [{"phrase": "barbados", "count": 277}, {"phrase": "caribbean", "count": 82}, {"phrase": "island", "count": 79}, {"phrase": "tropical", "count": 50}, {"phrase": "scenery", "count": 48}, {"phrase": "ocean", "count": 46}]}, {"admin1": "Saint Joseph", "city": "Bathsheba", "total": 1070, "top_phrases": [{"phrase": "barbados", "count": 191}, {"phrase": "caribbean", "count": 73}, {"phrase": "scenery", "count": 68}, {"phrase": "ocean", "count": 63}, {"phrase": "island", "count": 58}, {"phrase": "tropical", "count": 53}]}, {"admin1": "Christ Church", "city": "Oistins", "total": 623, "top_phrases": [{"phrase": "barbados", "count": 209}, {"phrase": "caribbean", "count": 69}, {"phrase": "beach", "count": 57}, {"phrase": "ocean", "count": 52}, {"phrase": "sea", "count": 38}, {"phrase": "fish", "count": 16}]}, {"admin1": "Saint Andrew", "city": "Greenland", "total": 379, "top_phrases": [{"phrase": "barbados", "count": 63}, {"phrase": "island", "count": 22}, {"phrase": "water", "count": 19}, {"phrase": "atlantic", "count": 18}, {"phrase": "coast", "count": 18}, {"phrase": "coastline", "count": 18}]}, {"admin1": "Saint Philip", "city": "Crane", "total": 283, "top_phrases": [{"phrase": "barbados", "count": 52}, {"phrase": "caribbean", "count": 30}, {"phrase": "kristina cruises", "count": 18}, {"phrase": "outdoors", "count": 15}, {"phrase": "sea", "count": 13}, {"phrase": "background", "count": 12}]}, {"admin1": "Saint Lucy", "city": "Checker Hall", "total": 158, "top_phrases": [{"phrase": "barbados", "count": 28}, {"phrase": "caribbean", "count": 12}, {"phrase": "sea", "count": 7}, {"phrase": "island", "count": 6}, {"phrase": "autopanopro", "count": 5}, {"phrase": "backside", "count": 5}]}, {"admin1": "Saint John", "city": "Four Cross Roads", "total": 133, "top_phrases": [{"phrase": "barbados", "count": 36}, {"phrase": "caribbean", "count": 10}, {"phrase": "islands", "count": 8}, {"phrase": "ocean", "count": 6}, {"phrase": "island", "count": 6}, {"phrase": "beach", "count": 5}]}, {"admin1": "Saint Thomas", "city": "Welchman Hall", "total": 131, "top_phrases": [{"phrase": "barbados", "count": 39}, {"phrase": "cave", "count": 15}, {"phrase": "harrison%27s cave", "count": 14}, {"phrase": "caribbean", "count": 14}, {"phrase": "gun hill signal station", "count": 11}, {"phrase": "green", "count": 4}]}, {"admin1": "Saint Peter", "city": "Speightstown", "total": 84, "top_phrases": [{"phrase": "barbados", "count": 20}, {"phrase": "sea", "count": 8}, {"phrase": "ocean", "count": 7}, {"phrase": "beach", "count": 7}, {"phrase": "sunset", "count": 5}, {"phrase": "sand", "count": 4}]}], "samples": [{"photoid": 436727981, "key": "180f9c4361035b319fe438b581c3ba2", "shard": "180", "lat": 13.105467, "lon": -59.444189, "admin1": "Saint Philip", "city": "Crane", "title": "Kitesurfing", "usertags": "1280x800,atlantic,background,barbados,blue,caribbean,crane,crane+beach,desktop,desktop+background,desktop+wallpaper,kitesurfers,kitesurfing,ocean,sea,the+crane,turquoise,wallpaper,wallpapers,water,wes", "downloadurl": "http://farm1.staticflickr.com/185/436727981_361f00191c.jpg", "top_phrases": ["atlantic", "background", "barbados", "blue", "caribbean", "crane", "crane beach", "desktop", "desktop background", "desktop wallpaper"]}, {"photoid": 8057464392, "key": "8406e5aa9a6addf837745de4039974d", "shard": "840", "lat": 13.095717, "lon": -59.618554, "admin1": "Saint Michael", "city": "Bridgetown", "title": "8P-BHB+at+Bridgetown+Heliport+2008", "usertags": "", "downloadurl": "http://farm9.staticflickr.com/8316/8057464392_10d4e73724.jpg", "top_phrases": []}, {"photoid": 8715393759, "key": "840259afb33d56e750d1f05e59248e", "shard": "840", "lat": 13.0981, "lon": -59.612524, "admin1": "Saint Michael", "city": "Bridgetown", "title": "Bridgetown+-+St.+Michael%27s+Cathedral+and+Churchyard", "usertags": "2013,anglican,atlantic,barbados,bridgetown,caribbean,cathedral,cemetery,church,churchyard,cruise,ocean,saint+michael,st+michael,tower", "downloadurl": "http://farm8.staticflickr.com/7294/8715393759_cce2443e26.jpg", "top_phrases": ["anglican", "atlantic", "barbados", "bridgetown", "caribbean", "cathedral", "cemetery", "church", "churchyard", "cruise"]}, {"photoid": 493992733, "key": "b81f5eee9fa3467d201d683cdc412bf", "shard": "b81", "lat": 13.095529, "lon": -59.615764, "admin1": "Saint Michael", "city": "Bridgetown", "title": "heroes+square", "usertags": "barbados,bridgetown", "downloadurl": "http://farm1.staticflickr.com/192/493992733_34ea92cf61.jpg", "top_phrases": ["barbados", "bridgetown"]}, {"photoid": 3395466140, "key": "c0133c9a88bb80bf2890643a3f1c6cb", "shard": "c01", "lat": 13.102118, "lon": -59.62881, "admin1": "Saint Michael", "city": "Bridgetown", "title": "Aerials+from+flight+from+Manchester+to+Barbados", "usertags": "barbados,caribbean,cruise,p%26o,thompsonfly,ventura", "downloadurl": "http://farm4.staticflickr.com/3636/3395466140_6fd2b60ed4.jpg", "top_phrases": ["barbados", "caribbean", "cruise", "p%26o", "thompsonfly", "ventura"]}, {"photoid": 1289910442, "key": "e81d12efc27c7974acf5fec3183a9d6", "shard": "e81", "lat": 13.218555, "lon": -59.644088, "admin1": "Saint Peter", "city": "Speightstown", "title": "Barbados+Sunset", "usertags": "barbados,fdsflickrtoys,ocean,sand,sea,sun,sunset", "downloadurl": "http://farm2.staticflickr.com/1412/1289910442_5e246edfa4.jpg", "top_phrases": ["barbados", "fdsflickrtoys", "ocean", "sand", "sea", "sun", "sunset"]}, {"photoid": 525617062, "key": "f816c2764d9074cf843a3bd7538360", "shard": "f81", "lat": 13.074302, "lon": -59.589019, "admin1": "Saint Michael", "city": "Bridgetown", "title": "025+-+Oceanfront+Grill", "usertags": "2007,barbados,christian,may,reflection,self+portrait,shannon", "downloadurl": "http://farm2.staticflickr.com/1205/525617062_bc3d6d0e40.jpg", "top_phrases": ["barbados", "christian", "may", "reflection", "self", "shannon"]}, {"photoid": 493992745, "key": "120807f652b6c9555ac2f88b1ea80e4", "shard": "120", "lat": 13.095529, "lon": -59.615764, "admin1": "Saint Michael", "city": "Bridgetown", "title": "jubilee+gardens", "usertags": "barbados,bridgetown", "downloadurl": "http://farm1.staticflickr.com/201/493992745_4f2aa67d24.jpg", "top_phrases": ["barbados", "bridgetown"]}, {"photoid": 543420796, "key": "560184382118d47c2b6269aa9b0c3", "shard": "560", "lat": 13.076255, "lon": -59.604061, "admin1": "Saint Michael", "city": "Bridgetown", "title": "221+-+Turtle+Nest+Beach+Bar", "usertags": "amaryllis+beach+resort,beach,ocean,turtle+nest+beach+bar,water", "downloadurl": "http://farm2.staticflickr.com/1336/543420796_45c4e69b48.jpg", "top_phrases": ["amaryllis beach resort", "beach", "ocean", "turtle nest beach bar", "water"]}, {"photoid": 4179393038, "key": "b61b0565456bd384ef2ac81c5bcd6ab", "shard": "b61", "lat": 13.191482, "lon": -59.533367, "admin1": "Saint Joseph", "city": "Bathsheba", "title": "Andromeda+Botanical+Gardens%2C+Barbados", "usertags": "2009,barbados,barbados+2009,caribbean,flora,flower,flowers,indies,island,ocean,park,plant,plants,scenery,tropical,west", "downloadurl": "http://farm3.staticflickr.com/2548/4179393038_58c190290d.jpg", "top_phrases": ["barbados", "barbados", "caribbean", "flora", "flower", "flowers", "indies", "island", "ocean", "park"]}, {"photoid": 8597156645, "key": "b61ede21020947e85c33ff7ae614b7", "shard": "b61", "lat": 13.07363, "lon": -59.590037, "admin1": "Saint Michael", "city": "Bridgetown", "title": "Former+hotel", "usertags": "accra,barbados,beach,caribbean,rockley,travel,vacation", "downloadurl": "http://farm9.staticflickr.com/8247/8597156645_003802da37.jpg", "top_phrases": ["accra", "barbados", "beach", "caribbean", "rockley"]}, {"photoid": 536557984, "key": "ba17b99d2a293b3892e3fa3ae82aacc", "shard": "ba1", "lat": 13.204547, "lon": -59.518372, "admin1": "Saint Joseph", "city": "Bathsheba", "title": "161+-+Hackleton+Cliff", "usertags": "2007,barbados,hackleton+cliff,may", "downloadurl": "http://farm2.staticflickr.com/1001/536557984_bc9b0fc7f2.jpg", "top_phrases": ["barbados", "hackleton cliff", "may"]}, {"photoid": 6481679369, "key": "ba16b4e4e1a9a282574826976ea6548", "shard": "ba1", "lat": 13.158047, "lon": -59.632669, "admin1": "Saint James", "city": "Holetown", "title": "Barracuda+%40+The+Cliff+Restaurant", "usertags": "barracuda,foodspotting,the+cliff+restaurant", "downloadurl": "http://farm8.staticflickr.com/7008/6481679369_e344cc3e93.jpg", "top_phrases": ["barracuda", "foodspotting", "cliff restaurant"]}, {"photoid": 6976862065, "key": "d61ced77c78d8cd7baf245b1de36a67", "shard": "d61", "lat": 13.187638, "lon": -59.587869, "admin1": "Saint Thomas", "city": "Welchman Hall", "title": "Harrison%27s+Cave", "usertags": "barbados,cave,fossils,harrison%27s+cave,s,stones,underground,wet", "downloadurl": "http://farm8.staticflickr.com/7056/6976862065_401a7a15f2.jpg", "top_phrases": ["barbados", "cave", "fossils", "harrison%27s cave", "stones", "underground", "wet"]}]}