{
  "year": 2014,
  "url": "https://en.wikipedia.org/wiki/2014_Kentucky_Derby",
  "finishers": [
    {
      "finish": 1,
      "post": 5,
      "horse": "California Chrome",
      "trainer": "Art Sherman",
      "jockey": "Victor Espinoza",
      "ml_odds_str": "5–2",
      "ml_odds": 2.5,
      "final_odds_str": "2.5",
      "final_odds": 2.5,
      "margin": "1 + 3 ⁄ 4"
    },
    {
      "finish": 2,
      "post": 16,
      "horse": "Commanding Curve",
      "trainer": "Dallas Stewart",
      "jockey": "Shaun Bridgmohan",
      "ml_odds_str": "50–1",
      "ml_odds": 50.0,
      "final_odds_str": "37.8",
      "final_odds": 37.8,
      "margin": "1 + 3 ⁄ 4"
    },
    {
      "finish": 3,
      "post": 4,
      "horse": "Danza",
      "trainer": "Todd Pletcher",
      "jockey": "Joe Bravo",
      "ml_odds_str": "10–1",
      "ml_odds": 10.0,
      "final_odds_str": "8.7",
      "final_odds": 8.7,
      "margin": "3"
    },
    {
      "finish": 4,
      "post": 19,
      "horse": "Wicked Strong",
      "trainer": "James Jerkens",
      "jockey": "Rajiv Maragh",
      "ml_odds_str": "8–1",
      "ml_odds": 8.0,
      "final_odds_str": "6.5",
      "final_odds": 6.5,
      "margin": "5 + 3 ⁄ 4"
    },
    {
      "finish": 5,
      "post": 6,
      "horse": "Samraat",
      "trainer": "Rick Violette Jr.",
      "jockey": "José Ortiz",
      "ml_odds_str": "15–1",
      "ml_odds": 15.0,
      "final_odds_str": "16.7",
      "final_odds": 16.7,
      "margin": "5 + 3 ⁄ 4"
    },
    {
      "finish": 6,
      "post": 11,
      "horse": "Dance With Fate",
      "trainer": "Peter Eurton",
      "jockey": "Corey Nakatani",
      "ml_odds_str": "20–1",
      "ml_odds": 20.0,
      "final_odds_str": "16.0",
      "final_odds": 16.0,
      "margin": "6 + 1 ⁄ 4"
    },
    {
      "finish": 7,
      "post": 18,
      "horse": "Ride On Curlin",
      "trainer": "William Gowan",
      "jockey": "Calvin Borel",
      "ml_odds_str": "15–1",
      "ml_odds": 15.0,
      "final_odds_str": "17.3",
      "final_odds": 17.3,
      "margin": "6 + 3 ⁄ 4"
    },
    {
      "finish": 8,
      "post": 13,
      "horse": "Medal Count",
      "trainer": "Dale Romans",
      "jockey": "Robby Albarado",
      "ml_odds_str": "20–1",
      "ml_odds": 20.0,
      "final_odds_str": "26.2",
      "final_odds": 26.2,
      "margin": "7 + 1 ⁄ 2"
    },
    {
      "finish": 9,
      "post": 12,
      "horse": "Chitu",
      "trainer": "Bob Baffert",
      "jockey": "Martin Garcia",
      "ml_odds_str": "20–1",
      "ml_odds": 20.0,
      "final_odds_str": "25.5",
      "final_odds": 25.5,
      "margin": "8"
    },
    {
      "finish": 10,
      "post": 7,
      "horse": "We Miss Artie",
      "trainer": "Todd Pletcher",
      "jockey": "Javier Castellano",
      "ml_odds_str": "50–1",
      "ml_odds": 50.0,
      "final_odds_str": "27.6",
      "final_odds": 27.6,
      "margin": "8 + 1 ⁄ 4"
    },
    {
      "finish": 11,
      "post": 8,
      "horse": "General A Rod",
      "trainer": "Michael J. Maker",
      "jockey": "Joel Rosario",
      "ml_odds_str": "15–1",
      "ml_odds": 15.0,
      "final_odds_str": "30.7",
      "final_odds": 30.7,
      "margin": "8 + 1 ⁄ 2"
    },
    {
      "finish": 12,
      "post": 15,
      "horse": "Intense Holiday",
      "trainer": "Todd Pletcher",
      "jockey": "John Velazquez",
      "ml_odds_str": "12–1",
      "ml_odds": 12.0,
      "final_odds_str": "14.1",
      "final_odds": 14.1,
      "margin": "9 + 1 ⁄ 4"
    },
    {
      "finish": 13,
      "post": 17,
      "horse": "Candy Boy",
      "trainer": "John W. Sadler",
      "jockey": "Gary Stevens",
      "ml_odds_str": "20–1",
      "ml_odds": 20.0,
      "final_odds_str": "9.4",
      "final_odds": 9.4,
      "margin": "12"
    },
    {
      "finish": 14,
      "post": 3,
      "horse": "Uncle Sigh",
      "trainer": "Gary Contessa",
      "jockey": "Irad Ortiz Jr.",
      "ml_odds_str": "30–1",
      "ml_odds": 30.0,
      "final_odds_str": "30.8",
      "final_odds": 30.8,
      "margin": "16 + 1 ⁄ 4"
    },
    {
      "finish": 15,
      "post": 14,
      "horse": "Tapiture",
      "trainer": "Steve Asmussen",
      "jockey": "Ricardo Santana Jr.",
      "ml_odds_str": "15–1",
      "ml_odds": 15.0,
      "final_odds_str": "35.2",
      "final_odds": 35.2,
      "margin": "17 + 1 ⁄ 2"
    },
    {
      "finish": 16,
      "post": 2,
      "horse": "Harry's Holiday",
      "trainer": "Michael J. Maker",
      "jockey": "Corey Lanerie",
      "ml_odds_str": "50–1",
      "ml_odds": 50.0,
      "final_odds_str": "44.3",
      "final_odds": 44.3,
      "margin": "23 + 3 ⁄ 4"
    },
    {
      "finish": 17,
      "post": 9,
      "horse": "Vinceremos",
      "trainer": "Todd Pletcher",
      "jockey": "Joe Rocco Jr.",
      "ml_odds_str": "30–1",
      "ml_odds": 30.0,
      "final_odds_str": "49.7",
      "final_odds": 49.7,
      "margin": "29 + 1 ⁄ 2"
    },
    {
      "finish": 18,
      "post": 10,
      "horse": "Wildcat Red",
      "trainer": "Jose Garoffalo",
      "jockey": "Luis Saez",
      "ml_odds_str": "15–1",
      "ml_odds": 15.0,
      "final_odds_str": "18.6",
      "final_odds": 18.6,
      "margin": "29 + 1 ⁄ 2"
    },
    {
      "finish": 19,
      "post": 1,
      "horse": "Vicar's In Trouble",
      "trainer": "Michael J. Maker",
      "jockey": "Rosie Napravnik",
      "ml_odds_str": "30–1",
      "ml_odds": 30.0,
      "final_odds_str": "20.40",
      "final_odds": 20.4,
      "margin": "39 + 1 ⁄ 2"
    },
    {
      "finish": "scratched",
      "post": null,
      "horse": "Hoppertunity",
      "trainer": "Bob Baffert",
      "jockey": "Mike Smith",
      "ml_odds_str": "SCR",
      "ml_odds": null,
      "final_odds_str": "-",
      "final_odds": null,
      "margin": "-"
    },
    {
      "finish": "scratched",
      "post": null,
      "horse": "Pablo del Monte",
      "trainer": "Wesley Ward",
      "jockey": "Jeffrey Sanchez",
      "ml_odds_str": "SCR",
      "ml_odds": null,
      "final_odds_str": "-",
      "final_odds": null,
      "margin": "-"
    }
  ],
  "track_condition": null,
  "fractions": null,
  "splits": [
    "23.04",
    "24.33",
    "24.34",
    "25.65",
    "26.21"
  ],
  "winning_time": "2:03.66"
}